sotalab/__init__.py
sotalab/core/__init__.py
sotalab/core/config/__init__.py
sotalab/core/config/registry.py
sotalab/core/config/spec.py
sotalab/core/config/type_utils.py
sotalab/core/env.py
sotalab/core/program.py
sotalab/core/utils/__init__.py
sotalab/core/utils/singleton.py
sotalab/core/utils/yaml.py
sotalab_core-0.1.6.dist-info/LICENSE
sotalab_core-0.1.6.dist-info/WHEEL
sotalab_core-0.1.6.dist-info/METADATA
sotalab_core-0.1.6.dist-info/RECORD
