Metadata-Version: 2.1
Name: sotalab-core
Version: 0.1.6
Summary: SotaLab
License: MIT
Author: Ming Yang
Author-email: ymviv@qq.com
Requires-Python: >=3.8,<4.0
Classifier: License :: OSI Approved :: MIT License
Classifier: Programming Language :: Python :: 3
Classifier: Programming Language :: Python :: 3.10
Classifier: Programming Language :: Python :: 3.8
Classifier: Programming Language :: Python :: 3.9
Requires-Dist: ruamel.yaml (>=0.16.12,<0.17.0)
